gce_rescue/__init__.py
gce_rescue/config.py
gce_rescue/gce.py
gce_rescue/gce_test.py
gce_rescue/messages.py
gce_rescue/messages_test.py
gce_rescue/startup-script.txt
gce_rescue/utils.py
gce_rescue/utils_test.py
gce_rescue/bin/__init__.py
gce_rescue/bin/rescue.py
gce_rescue/tasks/__init__.py
gce_rescue/tasks/actions.py
gce_rescue/tasks/backup.py
gce_rescue/tasks/backup_test.py
gce_rescue/tasks/disks.py
gce_rescue/tasks/disks_test.py
gce_rescue/tasks/keeper.py
gce_rescue/tasks/metadata.py
gce_rescue/tasks/metadata_test.py
gce_rescue/tasks/operations.py
gce_rescue/tasks/operations_test.py
gce_rescue/tasks/pre_validations.py
gce_rescue/tasks/validations/__init__.py
gce_rescue/tasks/validations/api.py
gce_rescue/tasks/validations/authentication.py
gce_rescue/tasks/validations/authorization.py
gce_rescue/test/__init__.py
gce_rescue/test/mocks.py
gce_rescue-0.4.dist-info/LICENSE
gce_rescue-0.4.dist-info/METADATA
gce_rescue-0.4.dist-info/WHEEL
gce_rescue-0.4.dist-info/entry_points.txt
gce_rescue-0.4.dist-info/top_level.txt
gce_rescue-0.4.dist-info/RECORD
