Metadata-Version: 2.1
Name: gce-rescue
Version: 0.4
Summary: GCE Rescue - Boot your GCE VM in rescue mode.
Home-page: https://github.com/googlecloudplatform/gce-rescue
Author: Halley de Souza
Author-email: gce-rescue-dev@google.com
License: Apache-2.0
Platform: UNKNOWN
Classifier: License :: OSI Approved :: Apache Software License
Classifier: Operating System :: OS Independent
Classifier: Programming Language :: Python :: 3.7
Classifier: Programming Language :: Python :: 3.8
Classifier: Programming Language :: Python :: 3.9
Classifier: Programming Language :: Python :: 3.10
Classifier: Programming Language :: Python :: 3.11
Classifier: Programming Language :: Python :: 3.12
Classifier: Topic :: System :: Boot
Classifier: Topic :: System :: Boot :: Init
Classifier: Topic :: System :: Recovery Tools
Classifier: Topic :: System :: System Shells
Classifier: Topic :: System :: Systems Administration
License-File: LICENSE
Requires-Dist: absl-py (>=1.2.0)
Requires-Dist: google-api-python-client
Requires-Dist: google-auth
